ods_utils_py/__init__.py
ods_utils_py/_config.py
ods_utils_py/_requests_utils.py
ods_utils_py/get_all_dataset_ids.py
ods_utils_py/get_dataset_custom_view.py
ods_utils_py/get_dataset_license.py
ods_utils_py/get_dataset_metadata.py
ods_utils_py/get_dataset_metadata_temporal_period.py
ods_utils_py/get_dataset_title.py
ods_utils_py/get_number_of_datasets.py
ods_utils_py/get_template_metadata.py
ods_utils_py/get_uid_by_id.py
ods_utils_py/set_dataset_license.py
ods_utils_py/set_dataset_metadata_temporal_coverage_end_date.py
ods_utils_py/set_dataset_metadata_temporal_coverage_start_date.py
ods_utils_py/set_dataset_metadata_temporal_period.py
ods_utils_py/set_dataset_public.py
ods_utils_py/set_template_metadata.py
ods_utils_py-0.2.6.dist-info/licenses/LICENSE
ods_utils_py-0.2.6.dist-info/METADATA
ods_utils_py-0.2.6.dist-info/WHEEL
ods_utils_py-0.2.6.dist-info/top_level.txt
ods_utils_py-0.2.6.dist-info/RECORD
