Metadata-Version: 2.4
Name: ods_utils_py
Version: 0.2.6
Summary: A python wrapper library for the ODS Automation API
Home-page: https://github.com/opendatasoft/ods-utils-py/
Author: Renato FARRUGGIO
Author-email: renato.farruggio@bs.ch
License: MIT License
Classifier: Programming Language :: Python :: 3
Classifier: License :: OSI Approved :: MIT License
Classifier: Operating System :: OS Independent
Requires-Python: >=3.11
License-File: LICENSE
Requires-Dist: certifi>=2025.11.12
Requires-Dist: charset-normalizer>=3.4.4
Requires-Dist: colorama>=0.4.6
Requires-Dist: idna>=3.11
Requires-Dist: iniconfig>=2.3.0
Requires-Dist: packaging>=25.0
Requires-Dist: pluggy>=1.6.0
Requires-Dist: pytest>=9.0.2
Requires-Dist: python-dotenv>=1.2.1
Requires-Dist: requests>=2.32.5
Requires-Dist: setuptools>=80.9.0
Requires-Dist: six>=1.17.0
Requires-Dist: tzdata>=2025.2
Requires-Dist: urllib3>=2.6.2
Dynamic: author
Dynamic: author-email
Dynamic: classifier
Dynamic: description
Dynamic: description-content-type
Dynamic: home-page
Dynamic: license
Dynamic: license-file
Dynamic: requires-dist
Dynamic: requires-python
Dynamic: summary
